grip/__init__.py
grip/__main__.py
grip/_compat.py
grip/api.py
grip/app.py
grip/assets.py
grip/browser.py
grip/command.py
grip/constants.py
grip/exceptions.py
grip/patcher.py
grip/readers.py
grip/renderers.py
grip/settings.py
grip/static/favicon.ico
grip/static/octicons/octicons.css
grip/static/octicons/octicons.eot
grip/static/octicons/octicons.svg
grip/static/octicons/octicons.ttf
grip/static/octicons/octicons.woff
grip/static/octicons/octicons.woff2
grip/templates/base.html
grip/templates/index.html
grip/templates/limit.html
grip/vendor/__init__.py
grip/vendor/mdx_urlize.py
grip/vendor/six.py
grip-4.6.2.dist-info/AUTHORS.md
grip-4.6.2.dist-info/LICENSE
grip-4.6.2.dist-info/METADATA
grip-4.6.2.dist-info/WHEEL
grip-4.6.2.dist-info/entry_points.txt
grip-4.6.2.dist-info/top_level.txt
grip-4.6.2.dist-info/RECORD
